translation/__init__.py
translation/data/deepl_languages.json
translation/data/general_languages.json
translation/data/google_languages.json
translation/engines.py
translation/engines_private.py
translation/languages.py
translation/qa.py
harken_translation-0.1.1.8.dist-info/METADATA
harken_translation-0.1.1.8.dist-info/WHEEL
harken_translation-0.1.1.8.dist-info/RECORD
